riftgun/__init__.py
riftgun/cog.py
riftgun/converters.py
riftgun/oneway.py
riftgun-1.0.2.dist-info/LICENSE
riftgun-1.0.2.dist-info/METADATA
riftgun-1.0.2.dist-info/WHEEL
riftgun-1.0.2.dist-info/top_level.txt
riftgun-1.0.2.dist-info/RECORD
