Metadata-Version: 2.1
Name: riftgun
Version: 1.0.2
Summary: A new module for providing easy remote support with discord bots
Home-page: https://github.com/dragdev-studios/RiftGun
Author: EEKIM10
Author-email: eek@clicksminuteper.net
License: Creative Commons Attribution-NonCommercial-NoDerivatives 4.0 International Public License
Platform: UNKNOWN
